README.md
setup.py
keras_utils/__init__.py
keras_utils/callbacks.py
keras_utils.egg-info/PKG-INFO
keras_utils.egg-info/SOURCES.txt
keras_utils.egg-info/dependency_links.txt
keras_utils.egg-info/requires.txt
keras_utils.egg-info/top_level.txt