Metadata-Version: 2.1
Name: keras-utils
Version: 1.0.12
Summary: Extended utilities for Keras
Home-page: https://github.com/eitankos/keras-utils
Author: Eitan Kosman
Author-email: eitan.kosman@gmail.com
License: UNKNOWN
Keywords: keras utilities
Platform: UNKNOWN
Classifier: Intended Audience :: Developers
Classifier: License :: OSI Approved :: MIT License
Classifier: Topic :: Software Development :: Libraries
Classifier: Programming Language :: Python :: 2
Classifier: Programming Language :: Python :: 2.7
Classifier: Programming Language :: Python :: 3
Classifier: Programming Language :: Python :: 3.4
Classifier: Programming Language :: Python :: 3.5
Classifier: Programming Language :: Python :: 3.6
